kcu/__init__.py
kcu/filelock.py
kcu/kjson.py
kcu/kpath.py
kcu/ktime.py
kcu/rand.py
kcu/request.py
kcu/sh.py
kcu/strings.py
kcu/strio.py
kcu-0.0.73.dist-info/METADATA
kcu-0.0.73.dist-info/WHEEL
kcu-0.0.73.dist-info/top_level.txt
kcu-0.0.73.dist-info/RECORD
