Metadata-Version: 2.1
Name: kcu
Version: 0.0.73
Summary: some python utility methods that I often use compiled in a package
Home-page: https://github.com/kkristof200/py_common_utils
Author: Kristof
License: UNKNOWN
Platform: UNKNOWN
Classifier: Programming Language :: Python :: 3
Classifier: License :: OSI Approved :: MIT License
Classifier: Operating System :: OS Independent
Requires-Python: >=3.5
